LICENSE
MANIFEST.in
README.rst
setup.py
django_organice_theme_fullpage.egg-info/PKG-INFO
django_organice_theme_fullpage.egg-info/SOURCES.txt
django_organice_theme_fullpage.egg-info/dependency_links.txt
django_organice_theme_fullpage.egg-info/not-zip-safe
django_organice_theme_fullpage.egg-info/requires.txt
django_organice_theme_fullpage.egg-info/top_level.txt
organice_theme_fullpage/__init__.py
organice_theme_fullpage/static/css/gh-fork-ribbon.css
organice_theme_fullpage/static/css/gh-fork-ribbon.ie.css
organice_theme_fullpage/static/css/styles.css
organice_theme_fullpage/static/js/fullpage_start.js
organice_theme_fullpage/static/js/jquery.easings.min.js
organice_theme_fullpage/static/js/jquery.slimscroll.min.js
organice_theme_fullpage/static/js/scripts.js
organice_theme_fullpage/templates/base.html
organice_theme_fullpage/templates/fullpage.html
organice_theme_fullpage/templates/skeleton.html