Metadata-Version: 1.1
Name: django-organice-theme-fullpage
Version: 0.3
Summary: A responsive full-page theme for django-organice.
Home-page: http://organice.io/themes/
Author: Peter Bitter
Author-email: django@bittner.it
License: Apache 2.0
Keywords: organice,theme,django,python
Platform: UNKNOWN
Classifier: Development Status :: 3 - Alpha
Classifier: Environment :: Web Environment
Classifier: Framework :: Django
Classifier: Intended Audience :: Developers
Classifier: License :: OSI Approved :: Apache Software License
Classifier: Operating System :: OS Independent
Classifier: Programming Language :: Python
Classifier: Topic :: Office/Business :: Groupware
